combilog_handler/__init__.py
combilog_handler/loghandler.py
combilog_handler/socketerror.py
combilog_handler-1.0.16.dist-info/METADATA
combilog_handler-1.0.16.dist-info/WHEEL
combilog_handler-1.0.16.dist-info/top_level.txt
combilog_handler-1.0.16.dist-info/RECORD
