Metadata-Version: 2.1
Name: combilog-handler
Version: 1.0.16
Summary: Interfaces with inbuilt python logger to send logs to combilog aggregator.
Home-page: https://github.com/lewjc/combilog-pythonhandler
Author: Lewis Cummins
Author-email: lewisjcummins@hotmail.co.uk
License: UNKNOWN
Platform: UNKNOWN
Classifier: Programming Language :: Python :: 3
Classifier: License :: OSI Approved :: MIT License
Classifier: Operating System :: OS Independent
Requires-Python: >=3.7
Requires-Dist: websocket-client
Requires-Dist: asyncio
